kangaroo/__init__.py
kangaroo_build-1.0.13.24.dist-info/LICENSE
kangaroo_build-1.0.13.24.dist-info/METADATA
kangaroo_build-1.0.13.24.dist-info/WHEEL
kangaroo_build-1.0.13.24.dist-info/top_level.txt
kangaroo_build-1.0.13.24.dist-info/RECORD
